lime_python/__init__.py
lime_python/protocol/__init__.py
lime_python/protocol/command.py
lime_python/protocol/envelope.py
lime_python/protocol/identity.py
lime_python/protocol/message.py
lime_python/protocol/node.py
lime_python/protocol/notification.py
lime_python/protocol/reason.py
lime_python/protocol/serializable.py
lime_python/protocol/session.py
lime_python/protocol/client/__init__.py
lime_python/protocol/client/channel.py
lime_python/protocol/client/client_channel.py
lime_python/protocol/client/command_processor.py
lime_python/protocol/client/channels/__init__.py
lime_python/protocol/client/channels/command_channel.py
lime_python/protocol/client/channels/message_channel.py
lime_python/protocol/client/channels/notification_channel.py
lime_python/protocol/client/channels/session_channel.py
lime_python/protocol/constants/__init__.py
lime_python/protocol/constants/authentication_scheme.py
lime_python/protocol/constants/command_method.py
lime_python/protocol/constants/command_status.py
lime_python/protocol/constants/common_constants.py
lime_python/protocol/constants/content_types.py
lime_python/protocol/constants/notification_event.py
lime_python/protocol/constants/reason_code.py
lime_python/protocol/constants/session_compression.py
lime_python/protocol/constants/session_encryption.py
lime_python/protocol/constants/session_state.py
lime_python/protocol/listeners/__init__.py
lime_python/protocol/listeners/command_listener.py
lime_python/protocol/listeners/envelope_listener.py
lime_python/protocol/listeners/message_listener.py
lime_python/protocol/listeners/notification_listener.py
lime_python/protocol/listeners/session_listener.py
lime_python/protocol/network/__init__.py
lime_python/protocol/network/transport.py
lime_python/protocol/security/__init__.py
lime_python/protocol/security/authentication.py
lime_python/protocol/security/external_authentication.py
lime_python/protocol/security/guest_authentication.py
lime_python/protocol/security/key_authentication.py
lime_python-2.0.13.dist-info/LICENSE
lime_python-2.0.13.dist-info/METADATA
lime_python-2.0.13.dist-info/WHEEL
lime_python-2.0.13.dist-info/top_level.txt
lime_python-2.0.13.dist-info/RECORD
