Metadata-Version: 2.1
Name: lime-python
Version: 2.0.13
Summary: This module implements the LIME protocol
Home-page: https://github.com/chr0m1ng/lime-python
Author: Gabriel Santos <gabrielr@take.net>, Luis Araújo <luisc@take.net>
Author-email: gabrielr@take.net
License: apache-2.0
Keywords: lime,blip,chatbot
Platform: UNKNOWN
Classifier: Development Status :: 5 - Production/Stable
Classifier: Intended Audience :: Developers
Classifier: Topic :: Software Development :: Build Tools
Classifier: License :: OSI Approved :: Apache Software License
Classifier: Programming Language :: Python :: 3.7
Classifier: Programming Language :: Python :: 3.8
Classifier: Programming Language :: Python :: 3.9
Requires-Dist: pyhumps
